Metadata-Version: 1.0
Name: Clyther
Version: 0.4-beta
Summary: OpenCL Python integration
Home-page: http://srossross.github.com/Clyther/
Author: Enthought, Inc.
Author-email: srossross@enthought.com
License: BSD
Platform: Windows
Platform: Linux
Platform: Mac OS-X
Platform: Unix
Platform: Solaris
Classifier: Development Status :: 4 - Beta
Classifier: Intended Audience :: Developers
Classifier: Intended Audience :: Science/Research
Classifier: License :: OSI Approved :: BSD License
Classifier: Operating System :: MacOS
Classifier: Operating System :: Microsoft :: Windows
Classifier: Operating System :: OS Independent
Classifier: Operating System :: POSIX
Classifier: Operating System :: Unix
Classifier: Programming Language :: Python
Classifier: Topic :: Scientific/Engineering
Classifier: Topic :: Software Development
Classifier: Topic :: Software Development :: Libraries
